python_whiteprint/__init__.py
python_whiteprint/cli/__init__.py
python_whiteprint/cli/__main__.py
python_whiteprint/cli/_callback.py
python_whiteprint/cli/_click_app.py
python_whiteprint/cli/_logging.py
python_whiteprint/cli/cli_types.py
python_whiteprint/cli/entrypoint.py
python_whiteprint/cli/environment.py
python_whiteprint/cli/exceptions.py
python_whiteprint/cli/init.py
python_whiteprint/console.py
python_whiteprint/filesystem.py
python_whiteprint/git.py
python_whiteprint/loc.py
python_whiteprint/locale/base.pot
python_whiteprint/locale/base.pot.license
python_whiteprint/locale/fr_FR/LC_MESSAGES/messages.mo
python_whiteprint/locale/fr_FR/LC_MESSAGES/messages.po
python_whiteprint/locale/fr_FR/LC_MESSAGES/messages.po.license
python_whiteprint/nox.py
python_whiteprint/poetry.py
python_whiteprint/py.typed
python_whiteprint/version.py
python_whiteprint-0.10.0.dist-info/COPYING
python_whiteprint-0.10.0.dist-info/LICENSES/CC-BY-4.0.txt
python_whiteprint-0.10.0.dist-info/LICENSES/CC0-1.0.txt
python_whiteprint-0.10.0.dist-info/LICENSES/MIT.txt
python_whiteprint-0.10.0.dist-info/METADATA
python_whiteprint-0.10.0.dist-info/WHEEL
python_whiteprint-0.10.0.dist-info/entry_points.txt
python_whiteprint-0.10.0.dist-info/RECORD
