Metadata-Version: 2.1
Name: python_whiteprint
Version: 0.10.0
Summary: Generating Python projects using best practices
Home-page: https://github.com/RomainBrault/python-whiteprint
License: MIT
Keywords: Python,Cookiecutter,copier,template,rich,typer,nox,poetry,beartype,oci-image,container,docker,podman,ruff
Author: Romain Brault
Author-email: mail@romainbrault.com
Requires-Python: >=3.8, !=2.7.*, !=3.0.*, !=3.1.*, !=3.2.*, !=3.3.*, !=3.4.*, !=3.5.*, !=3.6.*, !=3.7.*
Classifier: Development Status :: 3 - Alpha
Classifier: Environment :: Console
Classifier: Intended Audience :: Developers
Classifier: License :: OSI Approved
Classifier: License :: OSI Approved :: MIT License
Classifier: Natural Language :: English
Classifier: Operating System :: OS Independent
Classifier: Programming Language :: Python
Classifier: Programming Language :: Python :: 3
Classifier: Programming Language :: Python :: 3.9
Classifier: Programming Language :: Python :: 3.10
Classifier: Programming Language :: Python :: 3 :: Only
Classifier: Programming Language :: Python :: 3.11
Classifier: Programming Language :: Python :: 3.8
Classifier: Typing :: Typed
Requires-Dist: beartype (>=0.15.1)
Requires-Dist: colorama (>=0.4.3)
Requires-Dist: copier (>=7.1.0)
Requires-Dist: jinja2-time (>=0.2.0)
Requires-Dist: platformdirs (>=3.2.0)
Requires-Dist: pygit2 (>=1.11.1)
Requires-Dist: pygithub (>=1.58.1)
Requires-Dist: python-slugify (>=8.0.1)
Requires-Dist: returns (>=0.22.0)
Requires-Dist: rich (>=12.5.0)
Requires-Dist: shellingham (>=1.3.0)
Requires-Dist: typer (>=0.7.0)
Requires-Dist: typing-extensions (>=4.5.0)
Project-URL: Documentation, https://RomainBrault.github.io/python-whiteprint/
Project-URL: Repository, https://github.com/RomainBrault/python-whiteprint.git
